LICENSE
fuchs/__init__.py
fuchs/cache.py
fuchs/main.py
fuchs/parser.py
fuchs/utils.py
wire_fuchs-0.1.0.dist-info/LICENSE
wire_fuchs-0.1.0.dist-info/WHEEL
wire_fuchs-0.1.0.dist-info/METADATA
wire_fuchs-0.1.0.dist-info/RECORD
