Metadata-Version: 2.1
Name: wire-fuchs
Version: 0.1.0
Summary: Template engine for smart foxes, in python
Home-page: https://github.com/cheetahbyte/fuchs
License: MIT
Keywords: template,python,web,webdevelopment,template-engine
Author: cheetahbyte
Author-email: bernerdoodle@outlook.de
Requires-Python: >=3.9,<4.0
Classifier: License :: OSI Approved :: MIT License
Classifier: Programming Language :: Python :: 3
Classifier: Programming Language :: Python :: 3.10
Classifier: Programming Language :: Python :: 3.9
Project-URL: Repository, https://github.com/cheetahbyte/fuchs
